<?xml version="1.0" encoding="UTF-8"?>
<Patch>
    <!-- 给每个境界的配置打补丁 -->
     <!-- 1 -->
    <Operation Class="PatchOperationAdd">
        <xpath>/Defs/HediffDef[defName = "RI_Hediff_Beginning"]/stages/li/statOffsets</xpath>
        <value>
            <LRE_ExpStoredValueOffset>200</LRE_ExpStoredValueOffset>
            <LRE_ExpAbsorptionValueOffset>15</LRE_ExpAbsorptionValueOffset>
        </value>
    </Operation>
    
    <!-- 2 -->
    <Operation Class="PatchOperationAdd">
        <xpath>/Defs/HediffDef[defName = "RI_Hediff_Foundation"]/stages/li/statOffsets</xpath>
        <value>
            <LRE_ExpStoredValueOffset>500</LRE_ExpStoredValueOffset>
            <LRE_ExpAbsorptionValueOffset>30</LRE_ExpAbsorptionValueOffset>
        </value>
    </Operation>
    <!-- 3 -->
    <Operation Class="PatchOperationAdd">
        <xpath>/Defs/HediffDef[defName = "RI_Hediff_CoreFormation"]/stages/li/statOffsets</xpath>
        <value>
            <LRE_ExpStoredValueOffset>1000</LRE_ExpStoredValueOffset>
            <LRE_ExpAbsorptionValueOffset>45</LRE_ExpAbsorptionValueOffset>
        </value>
    </Operation>
    <!-- 4 -->
    <Operation Class="PatchOperationAdd">
        <xpath>/Defs/HediffDef[defName = "RI_Hediff_CoreCoagulation"]/stages/li/statOffsets</xpath>
        <value>
            <LRE_ExpStoredValueOffset>1500</LRE_ExpStoredValueOffset>
            <LRE_ExpAbsorptionValueOffset>60</LRE_ExpAbsorptionValueOffset>
        </value>
    </Operation>
    <!-- 5 -->
    <Operation Class="PatchOperationAdd">
        <xpath>/Defs/HediffDef[defName = "RI_Hediff_CoreImmaculacy"]/stages/li/statOffsets</xpath>
        <value>
            <LRE_ExpStoredValueOffset>2000</LRE_ExpStoredValueOffset>
            <LRE_ExpAbsorptionValueOffset>75</LRE_ExpAbsorptionValueOffset>
        </value>
    </Operation>
    <!-- 6 -->
    <Operation Class="PatchOperationAdd">
        <xpath>/Defs/HediffDef[defName = "RI_Hediff_Shackle"]/stages/li/statOffsets</xpath>
        <value>
            <LRE_ExpStoredValueOffset>2500</LRE_ExpStoredValueOffset>
            <LRE_ExpAbsorptionValueOffset>90</LRE_ExpAbsorptionValueOffset>
        </value>
    </Operation>
    <!-- 7 -->
    <Operation Class="PatchOperationAdd">
        <xpath>/Defs/HediffDef[defName = "RI_Hediff_PrimordialSpiritBaby"]/stages/li/statOffsets</xpath>
        <value>
            <LRE_ExpStoredValueOffset>3000</LRE_ExpStoredValueOffset>
            <LRE_ExpAbsorptionValueOffset>105</LRE_ExpAbsorptionValueOffset>
        </value>
    </Operation>
    <!-- 8 -->
    <Operation Class="PatchOperationAdd">
        <xpath>/Defs/HediffDef[defName = "RI_Hediff_PrimordialSpiritMaturation"]/stages/li/statOffsets</xpath>
        <value>
            <LRE_ExpStoredValueOffset>6000</LRE_ExpStoredValueOffset>
            <LRE_ExpAbsorptionValueOffset>120</LRE_ExpAbsorptionValueOffset>
        </value>
    </Operation>
    <!-- 9 -->
    <Operation Class="PatchOperationAdd">
        <xpath>/Defs/HediffDef[defName = "RI_Hediff_PrimordialSpiritCombine"]/stages/li/statOffsets</xpath>
        <value>
            <LRE_ExpStoredValueOffset>8000</LRE_ExpStoredValueOffset>
            <LRE_ExpAbsorptionValueOffset>135</LRE_ExpAbsorptionValueOffset>
        </value>
    </Operation>
    <!-- 10 -->
    <Operation Class="PatchOperationAdd">
        <xpath>/Defs/HediffDef[defName = "RI_Hediff_Immortal"]/stages/li/statOffsets</xpath>
        <value>
            <LRE_ExpStoredValueOffset>10000</LRE_ExpStoredValueOffset>
            <LRE_ExpAbsorptionValueOffset>150</LRE_ExpAbsorptionValueOffset>
        </value>
    </Operation>
</Patch>